dbis_magicmongo/__init__.py
dbis_magicmongo/mongomagics.py
dbis_magicmongo-0.1.0.dist-info/METADATA
dbis_magicmongo-0.1.0.dist-info/WHEEL
dbis_magicmongo-0.1.0.dist-info/top_level.txt
dbis_magicmongo-0.1.0.dist-info/RECORD
